aiogossip/__init__.py
aiogossip/__main__.py
aiogossip/broker.py
aiogossip/config.py
aiogossip/debug.py
aiogossip/gossip.py
aiogossip/members.py
aiogossip/message_pb2.py
aiogossip/peer.py
aiogossip/topology.py
aiogossip/concurrency/__init__.py
aiogossip/concurrency/channel.py
aiogossip/concurrency/mutex.py
aiogossip/concurrency/taskmanager.py
aiogossip/transport/__init__.py
aiogossip/transport/address.py
aiogossip/transport/codec.py
aiogossip/transport/transport.py
proto/message.proto
aiogossip-0.0.20.dist-info/METADATA
aiogossip-0.0.20.dist-info/WHEEL
aiogossip-0.0.20.dist-info/entry_points.txt
aiogossip-0.0.20.dist-info/top_level.txt
aiogossip-0.0.20.dist-info/RECORD
