Metadata-Version: 2.1
Name: aiogossip
Version: 0.0.20
Summary: AsyncIO implementation of Gossip protocol
Author-email: Andrey Gubarev <andrey@andreygubarev.com>
License: MIT
Project-URL: Homepage, https://github.com/andreygubarev/python-aiogossip/
Requires-Dist: networkx ==2.8.8
Requires-Dist: protobuf ==4.21.12
